threeML/__init__.py
threeML/_version.py
threeML/analysis_results.py
threeML/data_list.py
threeML/plugin_prototype.py
threeML/random_variates.py
threeML/bayesian/__init__.py
threeML/bayesian/autoemcee_sampler.py
threeML/bayesian/bayesian_analysis.py
threeML/bayesian/dynesty_sampler.py
threeML/bayesian/emcee_sampler.py
threeML/bayesian/multinest_sampler.py
threeML/bayesian/nautilus_sampler.py
threeML/bayesian/sampler_base.py
threeML/bayesian/tutorial_material.py
threeML/bayesian/ultranest_sampler.py
threeML/bayesian/zeus_sampler.py
threeML/catalogs/Fermi.py
threeML/catalogs/FermiGBM.py
threeML/catalogs/FermiLAT.py
threeML/catalogs/FermiLLE.py
threeML/catalogs/Swift.py
threeML/catalogs/VirtualObservatoryCatalog.py
threeML/catalogs/__init__.py
threeML/catalogs/catalog_utils.py
threeML/classicMLE/__init__.py
threeML/classicMLE/goodness_of_fit.py
threeML/classicMLE/joint_likelihood.py
threeML/classicMLE/joint_likelihood_set.py
threeML/classicMLE/likelihood_ratio_test.py
threeML/config/__init__.py
threeML/config/catalog_structure.py
threeML/config/config.py
threeML/config/config_structure.py
threeML/config/config_utils.py
threeML/config/fitting_structure.py
threeML/config/plotting_structure.py
threeML/config/plugin_structure.py
threeML/config/point_source_structure.py
threeML/data/default_style.yml
threeML/data/doc_config.yml
threeML/data/fermipy_basic_config.yml
threeML/data/ogip_test_gbm_b0.rsp2
threeML/data/ogip_test_gbm_n6.rsp
threeML/data/ogip_test_xmm_pn.arf
threeML/data/ogip_test_xmm_pn.rmf
threeML/data/threeml.mplstyle
threeML/data/threeml_docs.mplstyle
threeML/data/datasets/example_integral.pha
threeML/data/datasets/example_integral.rsp
threeML/data/datasets/example_integral_spi.pha
threeML/data/datasets/example_integral_spi.rsp
threeML/data/datasets/glg_cspec_n3_bn080916009_v00.rsp2
threeML/data/datasets/glg_cspec_n3_bn080916009_v01.pha
threeML/data/datasets/glg_cspec_n3_bn080916009_v07.rsp
threeML/data/datasets/glg_tte_n3_bn080916009_v01.fit.gz
threeML-2.4.2.dist-info/LICENSE
threeML-2.4.2.dist-info/METADATA
threeML-2.4.2.dist-info/WHEEL
threeML-2.4.2.dist-info/top_level.txt
threeML-2.4.2.dist-info/RECORD
