Metadata-Version: 2.1
Name: threeML
Version: 2.4.2
Summary: The Multi-Mission Maximum Likelihood framework
Home-page: https://github.com/threeml/threeML
Author: Giacomo Vianello
Author-email: giacomo.vianello@gmail.com
License: BSD-3
Project-URL: Documentation, https://threeml.readthedocs.io
Project-URL: Bug Tracker, https://github.com/threeML/threeML/issues
Project-URL: Source Code, https://github.com/threeML/threeML
Keywords: Likelihood,Multi-mission,3ML,HAWC,Fermi,HESS,joint,fit,bayesian,multi-wavelength
Classifier: Development Status :: 5 - Production/Stable
Classifier: Topic :: Scientific/Engineering :: Astronomy
Classifier: Intended Audience :: Science/Research
Classifier: Operating System :: POSIX
Classifier: Programming Language :: Python :: 3.9
Classifier: Environment :: Console
License-File: LICENSE
Requires-Dist: numpy >=1.16
Requires-Dist: scipy >=1.4
Requires-Dist: emcee >=3
Requires-Dist: astropy
Requires-Dist: matplotlib <3.9
Requires-Dist: uncertainties
Requires-Dist: pyyaml >=5.1
Requires-Dist: dill
Requires-Dist: iminuit >=2.0
Requires-Dist: astromodels
Requires-Dist: astroquery
Requires-Dist: corner
Requires-Dist: pandas
Requires-Dist: requests
Requires-Dist: speclite >=0.11
Requires-Dist: ipython
Requires-Dist: ipyparallel
Requires-Dist: joblib
Requires-Dist: numexpr
Requires-Dist: dynesty
Requires-Dist: numba
Requires-Dist: numdifftools
Requires-Dist: tqdm >=4.56.0
Requires-Dist: colorama
Requires-Dist: omegaconf
Requires-Dist: ipywidgets
Requires-Dist: rich
Provides-Extra: docs
Requires-Dist: sphinx >=1.4 ; extra == 'docs'
Requires-Dist: sphinx-rtd-theme ; extra == 'docs'
Requires-Dist: nbsphinx ; extra == 'docs'
Requires-Dist: sphinx-autoapi ; extra == 'docs'
Provides-Extra: tests
Requires-Dist: pytest ; extra == 'tests'
